simple_video_utils/__init__.py
simple_video_utils/frames.py
simple_video_utils/metadata.py
simple_video_utils-0.0.3.dist-info/licenses/LICENSE
simple_video_utils-0.0.3.dist-info/METADATA
simple_video_utils-0.0.3.dist-info/WHEEL
simple_video_utils-0.0.3.dist-info/top_level.txt
simple_video_utils-0.0.3.dist-info/RECORD
