Metadata-Version: 2.4
Name: simple-video-utils
Version: 0.0.3
Summary: Shared utilities for processing videos for sign language.
Author-email: Amit Moryossef <amit@sign.mt>
License: MIT
Requires-Python: >=3.10
License-File: LICENSE
Requires-Dist: av
Requires-Dist: numpy
Provides-Extra: dev
Requires-Dist: ruff; extra == "dev"
Requires-Dist: pytest; extra == "dev"
Requires-Dist: pytest-xdist; extra == "dev"
Dynamic: license-file
